Workbook

Sheet Data_overview
A2: year → numeric, model year of the car
A3: make → text, brand name
A4: model → text, car model
A5: trim → text, version of the model
A6: body → text, body type (SUV, Sedan, etc.)
A7: transmission → text
A8: vin → text, unique id
A9: state → text, location
A10: condition → numeric score
A11: odometer → numeric, mileage
A12: color → text
A13: interior → text
... A17: saledate → text → converted to sale_year

Sheet Data_quality_check
A1: sellingprice | E1: condition | I1: odometer
A2: Count | B2: =COUNT(Table1[sellingprice]) -> 1999 | E2: Count | F2: =COUNT(Table1[condition]) -> 1944 | I2: Count | J2: =COUNT((Table1[odometer])) -> 1999
A3: Average | B3: =AVERAGE(Table1[sellingprice]) -> 20393.274 | E3: Average | F3: =AVERAGE((Table1[condition])) -> 33.529321 | I3: Average | J3: =AVERAGE((Table1[odometer])) -> 35371.082
A4: Median | B4: =MEDIAN(Table1[sellingprice]) -> 18200 | E4: Median | F4: =MEDIAN((Table1[condition])) -> 38 | I4: Median | J4: =MEDIAN((Table1[odometer])) -> 32906
A5: Std Dev | B5: =_xlfn.STDEV.S((Table1[sellingprice])) -> 11708.734 | E5: Std Dev | F5: =_xlfn.STDEV.S((Table1[condition])) -> 13.332177 | I5: Std Dev | J5: =_xlfn.STDEV.S((Table1[odometer])) -> 29372.755
A6: Min | B6: =_xlfn.QUARTILE.INC((Table1[sellingprice]), C6) -> 1000 | C6: 0 | D6: =VLOOKUP(B6, car_sale_raw_dataset!O:R, 4, FALSE) -> Nissan Maxima 3.5 S | E6: Min | F6: =_xlfn.QUARTILE.INC((Table1[condition]), G6) -> 1 | G6: 0 | H6: =VLOOKUP(F6, car_sale_raw_dataset!$I:$R, 10, FALSE) -> Nissan Altima 2.5 S | I6: Min | J6: =_xlfn.QUARTILE.INC((Table1[odometer]), K6) -> 1 | K6: 0 | L6: =VLOOKUP(J6, car_sale_raw_dataset!$J:$R, 9, FALSE) -> Nissan Maxima 3.5 S
A7: 1st Quartile | B7: =_xlfn.QUARTILE.INC((Table1[sellingprice]), C7) -> 12100 | C7: 1 | E7: 1st Quartile | F7: =_xlfn.QUARTILE.INC((Table1[condition]), G7) -> 29 | G7: 1 | I7: 1st Quartile | J7: =_xlfn.QUARTILE.INC((Table1[odometer]), K7) -> 21323 | K7: 1
A8: 2nd Quartile | B8: =_xlfn.QUARTILE.INC((Table1[sellingprice]), C8) -> 18200 | C8: 2 | E8: 2nd Quartile | F8: =_xlfn.QUARTILE.INC((Table1[condition]), G8) -> 38 | G8: 2 | I8: 2nd Quartile | J8: =_xlfn.QUARTILE.INC((Table1[odometer]), K8) -> 32906 | K8: 2
A9: 3rd Quartile | B9: =_xlfn.QUARTILE.INC((Table1[sellingprice]), C9) -> 25000 | C9: 3 | E9: 3rd Quartile | F9: =_xlfn.QUARTILE.INC((Table1[condition]), G9) -> 43 | G9: 3 | I9: 3rd Quartile | J9: =_xlfn.QUARTILE.INC((Table1[odometer]), K9) -> 43261 | K9: 3
A10: Max | B10: =_xlfn.QUARTILE.INC((Table1[sellingprice]), C10) -> 154000 | C10: 4 | D10: =VLOOKUP(B10, car_sale_raw_dataset!O:R, 4, FALSE) -> Ferrari California Base | E10: Max | F10: =_xlfn.QUARTILE.INC((Table1[condition]), G10) -> 49 | G10: 4 | H10: =VLOOKUP(F10, car_sale_raw_dataset!$I:$R, 10, FALSE) -> Audi Q5 2.0T Premium Plus quattro | I10: Max | J10: =_xlfn.QUARTILE.INC((Table1[odometer]), K10) -> 999999 | K10: 4 | L10: =VLOOKUP(J10, car_sale_raw_dataset!$J:$R, 9, FALSE) -> Hyundai Elantra Coupe GS
A11: Mode | B11: =MODE((Table1[sellingprice])) -> 21000 | E11: Mode | F11: =MODE((Table1[condition])) -> 44 | I11: Mode | J11: =MODE((Table1[odometer])) -> 13661

Sheet Top5_Count_make_model_trim_body
A3: Row Labels | B3: Count of make | E3: Row Labels | F3: Count of model | I3: Row Labels | J3: Count of trim
A4: BMW | B4: 330 | E4: 3 Series | F4: 151 | I4: 328i | J4: 109
A5: Ford | B5: 137 | E5: Altima | F5: 118 | I5: Base | J5: 173
A6: Hyundai | B6: 189 | E6: Elantra | F6: 53 | I6: G37 Journey | J6: 139
A7: Infiniti | B7: 249 | E7: G Sedan | F7: 181 | I7: GLS | J7: 86
A8: Nissan | B8: 244 | E8: Sonata | F8: 54 | I8: SE | J8: 88
A9: Grand Total | B9: 1149 | E9: Grand Total | F9: 557 | I9: Grand Total | J9: 595
A12: Row Labels | B12: Count of body
A13: Convertible | B13: 103
A14: G Sedan | B14: 181
A15: Hatchback | B15: 145
A16: Sedan | B16: 961
A17: SUV | B17: 320
A18: Grand Total | B18: 1710

Sheet car_sale_raw_dataset
A1: year | B1: make | C1: model | D1: trim | E1: body | F1: transmission | G1: vin | H1: state | I1: condition | J1: odometer | K1: color | L1: interior | M1: seller | N1: mmr | O1: sellingprice | P1: saledate | Q1: sale_year | R1: car_full_name | S1: condition_flag | T1: price_flag
A2: 2015 | B2: Kia | C2: Sorento | D2: LX | E2: SUV | F2: automatic | G2: 5xyktca69fg566472 | H2: ca | I2: 5 | J2: 16639 | K2: white | L2: black | M2: kia motors america inc | N2: 20500 | O2: 21500 | P2: Tue Dec 16 2014 12:30:00 GMT-0800 (PST) | Q2: {=VALUE(INDEX(_xlfn.TEXTSPLIT(P2, " "), 4))} -> 2014 | R2: =_xlfn.TEXTJOIN(" ", TRUE, B2, C2, D2) -> Kia Sorento LX | S2: {=_xlfn.IFS(I2 >= 40, "High", I2>=20, "Medium", I2<20, "Low")} -> Low | T2: {=_xlfn.IFS(O2<18200, "Low", O2<=50000, "Medium", O2>50000, "High")} -> Medium | W2: Min | X2: =MIN(O:O) -> 1000
A3: 2015 | B3: Kia | C3: Sorento | D3: LX | E3: SUV | F3: automatic | G3: 5xyktca69fg561319 | H3: ca | I3: 5 | J3: 9393 | K3: white | L3: beige | M3: kia motors america inc | N3: 20800 | O3: 21500 | P3: Tue Dec 16 2014 12:30:00 GMT-0800 (PST) | Q3: {=VALUE(INDEX(_xlfn.TEXTSPLIT(P3, " "), 4))} -> 2014 | R3: =_xlfn.TEXTJOIN(" ", TRUE, B3, C3, D3) -> Kia Sorento LX | S3: {=_xlfn.IFS(I3 >= 40, "High", I3>=20, "Medium", I3<20, "Low")} -> Low | T3: {=_xlfn.IFS(O3<18200, "Low", O3<=50000, "Medium", O3>50000, "High")} -> Medium | W3: Median | X3: =MEDIAN(O:O) -> 18200
A4: 2014 | B4: BMW | C4: 3 Series | D4: 328i SULEV | E4: Sedan | F4: automatic | G4: wba3c1c51ek116351 | H4: ca | I4: 45 | J4: 1331 | K4: gray | L4: black | M4: financial services remarketing (lease) | N4: 31900 | O4: 30000 | P4: Thu Jan 15 2015 04:30:00 GMT-0800 (PST) | Q4: {=VALUE(INDEX(_xlfn.TEXTSPLIT(P4, " "), 4))} -> 2015 | R4: =_xlfn.TEXTJOIN(" ", TRUE, B4, C4, D4) -> BMW 3 Series 328i SULEV | S4: {=_xlfn.IFS(I4 >= 40, "High", I4>=20, "Medium", I4<20, "Low")} -> High | T4: {=_xlfn.IFS(O4<18200, "Low", O4<=50000, "Medium", O4>50000, "High")} -> Medium | W4: Max | X4: =MAX(O:O) -> 154000
A5: 2015 | B5: Volvo | C5: S60 | D5: T5 | E5: Sedan | F5: automatic | G5: yv1612tb4f1310987 | H5: ca | I5: 41 | J5: 14282 | K5: white | L5: black | M5: volvo na rep/world omni | N5: 27500 | O5: 27750 | P5: Thu Jan 29 2015 04:30:00 GMT-0800 (PST) | Q5: {=VALUE(INDEX(_xlfn.TEXTSPLIT(P5, " "), 4))} -> 2015 | R5: =_xlfn.TEXTJOIN(" ", TRUE, B5, C5, D5) -> Volvo S60 T5 | S5: {=_xlfn.IFS(I5 >= 40, "High", I5>=20, "Medium", I5<20, "Low")} -> High | T5: {=_xlfn.IFS(O5<18200, "Low", O5<=50000, "Medium", O5>50000, "High")} -> Medium
A6: 2014 | B6: BMW | C6: 6 Series Gran Coupe | D6: 650i | E6: Sedan | F6: automatic | G6: wba6b2c57ed129731 | H6: ca | I6: 43 | J6: 2641 | K6: gray | L6: black | M6: financial services remarketing (lease) | N6: 66000 | O6: 67000 | P6: Thu Dec 18 2014 12:30:00 GMT-0800 (PST) | Q6: {=VALUE(INDEX(_xlfn.TEXTSPLIT(P6, " "), 4))} -> 2014 | R6: =_xlfn.TEXTJOIN(" ", TRUE, B6, C6, D6) -> BMW 6 Series Gran Coupe 650i | S6: {=_xlfn.IFS(I6 >= 40, "High", I6>=20, "Medium", I6<20, "Low")} -> High | T6: {=_xlfn.IFS(O6<18200, "Low", O6<=50000, "Medium", O6>50000, "High")} -> High
A7: 2015 | B7: Nissan | C7: Altima | D7: 2.5 S | E7: Sedan | F7: automatic | G7: 1n4al3ap1fn326013 | H7: ca | I7: 1 | J7: 5554 | K7: gray | L7: black | M7: enterprise vehicle exchange / tra / rental / tulsa | N7: 15350 | O7: 10900 | P7: Tue Dec 30 2014 12:00:00 GMT-0800 (PST) | Q7: {=VALUE(INDEX(_xlfn.TEXTSPLIT(P7, " "), 4))} -> 2014 | R7: =_xlfn.TEXTJOIN(" ", TRUE, B7, C7, D7) -> Nissan Altima 2.5 S | S7: {=_xlfn.IFS(I7 >= 40, "High", I7>=20, "Medium", I7<20, "Low")} -> Low | T7: {=_xlfn.IFS(O7<18200, "Low", O7<=50000, "Medium", O7>50000, "High")} -> Low
A8: 2014 | B8: BMW | C8: M5 | D8: Base | E8: Sedan | F8: automatic | G8: wbsfv9c51ed593089 | H8: ca | I8: 34 | J8: 14943 | K8: black | L8: black | M8: the hertz corporation | N8: 69000 | O8: 65000 | P8: Wed Dec 17 2014 12:30:00 GMT-0800 (PST) | Q8: {=VALUE(INDEX(_xlfn.TEXTSPLIT(P8, " "), 4))} -> 2014 | R8: =_xlfn.TEXTJOIN(" ", TRUE, B8, C8, D8) -> BMW M5 Base | S8: {=_xlfn.IFS(I8 >= 40, "High", I8>=20, "Medium", I8<20, "Low")} -> Medium | T8: {=_xlfn.IFS(O8<18200, "Low", O8<=50000, "Medium", O8>50000, "High")} -> High | W8: =FIND(1, J:J) -> 1
A9: 2014 | B9: Chevrolet | C9: Cruze | D9: 1LT | E9: Sedan | F9: automatic | G9: 1g1pc5sb2e7128460 | H9: ca | I9: 2 | J9: 28617 | K9: black | L9: black | M9: enterprise vehicle exchange / tra / rental / tulsa | N9: 11900 | O9: 9800 | P9: Tue Dec 16 2014 13:00:00 GMT-0800 (PST) | Q9: {=VALUE(INDEX(_xlfn.TEXTSPLIT(P9, " "), 4))} -> 2014 | R9: =_xlfn.TEXTJOIN(" ", TRUE, B9, C9, D9) -> Chevrolet Cruze 1LT | S9: {=_xlfn.IFS(I9 >= 40, "High", I9>=20, "Medium", I9<20, "Low")} -> Low | T9: {=_xlfn.IFS(O9<18200, "Low", O9<=50000, "Medium", O9>50000, "High")} -> Low
A10: 2014 | B10: Audi | C10: A4 | D10: 2.0T Premium Plus quattro | E10: Sedan | F10: automatic | G10: wauffafl3en030343 | H10: ca | I10: 42 | J10: 9557 | K10: white | L10: black | M10: audi mission viejo | N10: 32100 | O10: 32250 | P10: Thu Dec 18 2014 12:00:00 GMT-0800 (PST) | Q10: {=VALUE(INDEX(_xlfn.TEXTSPLIT(P10, " "), 4))} -> 2014 | R10: =_xlfn.TEXTJOIN(" ", TRUE, B10, C10, D10) -> Audi A4 2.0T Premium Plus quattro | S10: {=_xlfn.IFS(I10 >= 40, "High", I10>=20, "Medium", I10<20, "Low")} -> High | T10: {=_xlfn.IFS(O10<18200, "Low", O10<=50000, "Medium", O10>50000, "High")} -> Medium
A11: 2014 | B11: Chevrolet | C11: Camaro | D11: LT | E11: Convertible | F11: automatic | G11: 2g1fb3d37e9218789 | H11: ca | I11: 3 | J11: 4809 | K11: red | L11: black | M11: d/m auto sales inc | N11: 26300 | O11: 17500 | P11: Tue Jan 20 2015 04:00:00 GMT-0800 (PST) | Q11: {=VALUE(INDEX(_xlfn.TEXTSPLIT(P11, " "), 4))} -> 2015 | R11: =_xlfn.TEXTJOIN(" ", TRUE, B11, C11, D11) -> Chevrolet Camaro LT | S11: {=_xlfn.IFS(I11 >= 40, "High", I11>=20, "Medium", I11<20, "Low")} -> Low | T11: {=_xlfn.IFS(O11<18200, "Low", O11<=50000, "Medium", O11>50000, "High")} -> Low
A12: 2014 | B12: Audi | C12: A6 | D12: 3.0T Prestige quattro | E12: Sedan | F12: automatic | G12: wauhgafc0en062916 | H12: ca | I12: 48 | J12: 14414 | K12: black | L12: black | M12: desert auto trade | N12: 47300 | O12: 49750 | P12: Tue Dec 16 2014 12:30:00 GMT-0800 (PST) | Q12: {=VALUE(INDEX(_xlfn.TEXTSPLIT(P12, " "), 4))} -> 2014 | R12: =_xlfn.TEXTJOIN(" ", TRUE, B12, C12, D12) -> Audi A6 3.0T Prestige quattro | S12: {=_xlfn.IFS(I12 >= 40, "High", I12>=20, "Medium", I12<20, "Low")} -> High | T12: {=_xlfn.IFS(O12<18200, "Low", O12<=50000, "Medium", O12>50000, "High")} -> Medium
A13: 2015 | B13: Kia | C13: Optima | D13: LX | E13: Sedan | F13: automatic | G13: 5xxgm4a73fg353538 | H13: ca | I13: 48 | J13: 2034 | K13: red | L13: tan | M13: kia motors finance | N13: 15150 | O13: 17700 | P13: Tue Dec 16 2014 12:00:00 GMT-0800 (PST) | Q13: {=VALUE(INDEX(_xlfn.TEXTSPLIT(P13, " "), 4))} -> 2014 | R13: =_xlfn.TEXTJOIN(" ", TRUE, B13, C13, D13) -> Kia Optima LX | S13: {=_xlfn.IFS(I13 >= 40, "High", I13>=20, "Medium", I13<20, "Low")} -> High | T13: {=_xlfn.IFS(O13<18200, "Low", O13<=50000, "Medium", O13>50000, "High")} -> Low
A14: 2015 | B14: Ford | C14: Fusion | D14: SE | E14: Sedan | F14: automatic | G14: 3fa6p0hdxfr145753 | H14: ca | I14: 2 | J14: 5559 | K14: white | L14: beige | M14: enterprise vehicle exchange / tra / rental / tulsa | N14: 15350 | O14: 12000 | P14: Tue Jan 13 2015 12:00:00 GMT-0800 (PST) | Q14: {=VALUE(INDEX(_xlfn.TEXTSPLIT(P14, " "), 4))} -> 2015 | R14: =_xlfn.TEXTJOIN(" ", TRUE, B14, C14, D14) -> Ford Fusion SE | S14: {=_xlfn.IFS(I14 >= 40, "High", I14>=20, "Medium", I14<20, "Low")} -> Low | T14: {=_xlfn.IFS(O14<18200, "Low", O14<=50000, "Medium", O14>50000, "High")} -> Low
A15: 2015 | B15: Kia | C15: Sorento | D15: LX | E15: SUV | F15: automatic | G15: 5xyktca66fg561407 | H15: ca | I15: 5 | J15: 14634 | K15: silver | L15: black | M15: kia motors america inc | N15: 20600 | O15: 21500 | P15: Tue Dec 16 2014 12:30:00 GMT-0800 (PST) | Q15: {=VALUE(INDEX(_xlfn.TEXTSPLIT(P15, " "), 4))} -> 2014 | R15: =_xlfn.TEXTJOIN(" ", TRUE, B15, C15, D15) -> Kia Sorento LX | S15: {=_xlfn.IFS(I15 >= 40, "High", I15>=20, "Medium", I15<20, "Low")} -> Low | T15: {=_xlfn.IFS(O15<18200, "Low", O15<=50000, "Medium", O15>50000, "High")} -> Medium
A16: 2014 | B16: Chevrolet | C16: Cruze | D16: 2LT | E16: Sedan | F16: automatic | G16: 1g1pe5sbxe7120097 | H16: ca | J16: 15686 | K16: blue | L16: black | M16: avis rac/san leandro | N16: 13900 | O16: 10600 | P16: Tue Dec 16 2014 12:00:00 GMT-0800 (PST) | Q16: {=VALUE(INDEX(_xlfn.TEXTSPLIT(P16, " "), 4))} -> 2014 | R16: =_xlfn.TEXTJOIN(" ", TRUE, B16, C16, D16) -> Chevrolet Cruze 2LT | S16: {=_xlfn.IFS(I16 >= 40, "High", I16>=20, "Medium", I16<20, "Low")} -> Low | T16: {=_xlfn.IFS(O16<18200, "Low", O16<=50000, "Medium", O16>50000, "High")} -> Low
A17: 2015 | B17: Nissan | C17: Altima | D17: 2.5 S | E17: Sedan | F17: automatic | G17: 1n4al3ap5fc124223 | H17: ca | I17: 2 | J17: 11398 | K17: black | L17: black | M17: enterprise vehicle exchange / tra / rental / tulsa | N17: 14750 | O17: 14100 | P17: Tue Dec 23 2014 12:00:00 GMT-0800 (PST) | Q17: {=VALUE(INDEX(_xlfn.TEXTSPLIT(P17, " "), 4))} -> 2014 | R17: =_xlfn.TEXTJOIN(" ", TRUE, B17, C17, D17) -> Nissan Altima 2.5 S | S17: {=_xlfn.IFS(I17 >= 40, "High", I17>=20, "Medium", I17<20, "Low")} -> Low | T17: {=_xlfn.IFS(O17<18200, "Low", O17<=50000, "Medium", O17>50000, "High")} -> Low
A18: 2015 | B18: Hyundai | C18: Sonata | D18: SE | E18: Sedan | F18: automatic | G18: 5npe24af4fh001562 | H18: ca | J18: 8311 | K18: red | L18: â€” | M18: avis tra | N18: 15200 | O18: 4200 | P18: Tue Dec 16 2014 13:00:00 GMT-0800 (PST) | Q18: {=VALUE(INDEX(_xlfn.TEXTSPLIT(P18, " "), 4))} -> 2014 | R18: =_xlfn.TEXTJOIN(" ", TRUE, B18, C18, D18) -> Hyundai Sonata SE | S18: {=_xlfn.IFS(I18 >= 40, "High", I18>=20, "Medium", I18<20, "Low")} -> Low | T18: {=_xlfn.IFS(O18<18200, "Low", O18<=50000, "Medium", O18>50000, "High")} -> Low
A19: 2014 | B19: Audi | C19: Q5 | D19: 2.0T Premium Plus quattro | E19: SUV | F19: automatic | G19: wa1lfafpxea085074 | H19: ca | I19: 49 | J19: 7983 | K19: white | L19: black | M19: audi north scottsdale | N19: 37100 | O19: 40000 | P19: Thu Dec 18 2014 12:30:00 GMT-0800 (PST) | Q19: {=VALUE(INDEX(_xlfn.TEXTSPLIT(P19, " "), 4))} -> 2014 | R19: =_xlfn.TEXTJOIN(" ", TRUE, B19, C19, D19) -> Audi Q5 2.0T Premium Plus quattro | S19: {=_xlfn.IFS(I19 >= 40, "High", I19>=20, "Medium", I19<20, "Low")} -> High | T19: {=_xlfn.IFS(O19<18200, "Low", O19<=50000, "Medium", O19>50000, "High")} -> Medium
A20: 2014 | B20: Chevrolet | C20: Camaro | D20: LS | E20: Coupe | F20: automatic | G20: 2g1fa1e39e9134494 | H20: ca | I20: 17 | J20: 13441 | K20: black | L20: black | M20: wells fargo dealer services | N20: 17750 | O20: 17000 | P20: Tue Dec 30 2014 15:00:00 GMT-0800 (PST) | Q20: {=VALUE(INDEX(_xlfn.TEXTSPLIT(P20, " "), 4))} -> 2014 | R20: =_xlfn.TEXTJOIN(" ", TRUE, B20, C20, D20) -> Chevrolet Camaro LS | S20: {=_xlfn.IFS(I20 >= 40, "High", I20>=20, "Medium", I20<20, "Low")} -> Low | T20: {=_xlfn.IFS(O20<18200, "Low", O20<=50000, "Medium", O20>50000, "High")} -> Low
A21: 2014 | B21: BMW | C21: 6 Series | D21: 650i | E21: Convertible | F21: automatic | G21: wbayp9c53ed169260 | H21: ca | I21: 34 | J21: 8819 | K21: black | L21: black | M21: the hertz corporation | N21: 68000 | O21: 67200 | P21: Wed Dec 17 2014 12:30:00 GMT-0800 (PST) | Q21: {=VALUE(INDEX(_xlfn.TEXTSPLIT(P21, " "), 4))} -> 2014 | R21: =_xlfn.TEXTJOIN(" ", TRUE, B21, C21, D21) -> BMW 6 Series 650i | S21: {=_xlfn.IFS(I21 >= 40, "High", I21>=20, "Medium", I21<20, "Low")} -> Medium | T21: {=_xlfn.IFS(O21<18200, "Low", O21<=50000, "Medium", O21>50000, "High")} -> High
A22: 2015 | B22: Chevrolet | C22: Impala | D22: LTZ | E22: Sedan | F22: automatic | G22: 2g1165s30f9103921 | H22: ca | I22: 19 | J22: 14538 | K22: silver | L22: black | M22: enterprise vehicle exchange / tra / rental / tulsa | N22: 24300 | O22: 7200 | P22: Tue Jul 07 2015 09:30:00 GMT-0700 (PDT) | Q22: {=VALUE(INDEX(_xlfn.TEXTSPLIT(P22, " "), 4))} -> 2015 | R22: =_xlfn.TEXTJOIN(" ", TRUE, B22, C22, D22) -> Chevrolet Impala LTZ | S22: {=_xlfn.IFS(I22 >= 40, "High", I22>=20, "Medium", I22<20, "Low")} -> Low | T22: {=_xlfn.IFS(O22<18200, "Low", O22<=50000, "Medium", O22>50000, "High")} -> Low
A23: 2014 | B23: BMW | C23: 5 Series | D23: 528i | E23: Sedan | F23: automatic | G23: wba5a5c51ed501631 | H23: ca | I23: 29 | J23: 25969 | K23: black | L23: black | M23: financial services remarketing (lease) | N23: 34200 | O23: 30000 | P23: Tue Feb 03 2015 04:30:00 GMT-0800 (PST) | Q23: {=VALUE(INDEX(_xlfn.TEXTSPLIT(P23, " "), 4))} -> 2015 | R23: =_xlfn.TEXTJOIN(" ", TRUE, B23, C23, D23) -> BMW 5 Series 528i | S23: {=_xlfn.IFS(I23 >= 40, "High", I23>=20, "Medium", I23<20, "Low")} -> Medium | T23: {=_xlfn.IFS(O23<18200, "Low", O23<=50000, "Medium", O23>50000, "High")} -> Medium
A24: 2014 | B24: Chevrolet | C24: Camaro | D24: LT | E24: Convertible | F24: automatic | G24: 2g1fb3d31e9134662 | H24: ca | J24: 33450 | K24: black | L24: black | M24: avis rac/san leandro | N24: 20100 | O24: 14700 | P24: Tue Dec 16 2014 12:00:00 GMT-0800 (PST) | Q24: {=VALUE(INDEX(_xlfn.TEXTSPLIT(P24, " "), 4))} -> 2014 | R24: =_xlfn.TEXTJOIN(" ", TRUE, B24, C24, D24) -> Chevrolet Camaro LT | S24: {=_xlfn.IFS(I24 >= 40, "High", I24>=20, "Medium", I24<20, "Low")} -> Low | T24: {=_xlfn.IFS(O24<18200, "Low", O24<=50000, "Medium", O24>50000, "High")} -> Low
A25: 2015 | B25: Audi | C25: A3 | D25: 1.8 TFSI Premium | E25: Sedan | F25: automatic | G25: wauacgff7f1002327 | H25: ca | I25: 49 | J25: 5826 | K25: gray | L25: black | M25: audi north scottsdale | N25: 24000 | O25: 23750 | P25: Thu Dec 18 2014 12:30:00 GMT-0800 (PST) | Q25: {=VALUE(INDEX(_xlfn.TEXTSPLIT(P25, " "), 4))} -> 2014 | R25: =_xlfn.TEXTJOIN(" ", TRUE, B25, C25, D25) -> Audi A3 1.8 TFSI Premium | S25: {=_xlfn.IFS(I25 >= 40, "High", I25>=20, "Medium", I25<20, "Low")} -> High | T25: {=_xlfn.IFS(O25<18200, "Low", O25<=50000, "Medium", O25>50000, "High")} -> Medium
A26: 2014 | B26: BMW | C26: 6 Series | D26: 650i | E26: Convertible | F26: automatic | G26: wbayp9c57ed169262 | H26: ca | I26: 38 | J26: 10736 | K26: black | L26: black | M26: the hertz corporation | N26: 67000 | O26: 65000 | P26: Tue Jan 06 2015 12:30:00 GMT-0800 (PST) | Q26: {=VALUE(INDEX(_xlfn.TEXTSPLIT(P26, " "), 4))} -> 2015 | R26: =_xlfn.TEXTJOIN(" ", TRUE, B26, C26, D26) -> BMW 6 Series 650i | S26: {=_xlfn.IFS(I26 >= 40, "High", I26>=20, "Medium", I26<20, "Low")} -> Medium | T26: {=_xlfn.IFS(O26<18200, "Low", O26<=50000, "Medium", O26>50000, "High")} -> High
A27: 2015 | B27: Hyundai | C27: Sonata | D27: SE | E27: Sedan | F27: automatic | G27: 5npe24af4fh038482 | H27: ca | J27: 9281 | K27: silver | L27: gray | M27: enterprise vehicle exchange / tra / rental / tulsa | N27: 15150 | O27: 8500 | P27: Tue Dec 16 2014 13:00:00 GMT-0800 (PST) | Q27: {=VALUE(INDEX(_xlfn.TEXTSPLIT(P27, " "), 4))} -> 2014 | R27: =_xlfn.TEXTJOIN(" ", TRUE, B27, C27, D27) -> Hyundai Sonata SE | S27: {=_xlfn.IFS(I27 >= 40, "High", I27>=20, "Medium", I27<20, "Low")} -> Low | T27: {=_xlfn.IFS(O27<18200, "Low", O27<=50000, "Medium", O27>50000, "High")} -> Low
A28: 2015 | B28: Volvo | C28: XC70 | D28: T6 | E28: Wagon | F28: automatic | G28: yv4902nb3f1198103 | H28: ca | I28: 42 | J28: 16506 | K28: brown | L28: brown | M28: volvo na rep/world omni | N28: 32100 | O28: 32500 | P28: Thu Feb 26 2015 04:30:00 GMT-0800 (PST) | Q28: {=VALUE(INDEX(_xlfn.TEXTSPLIT(P28, " "), 4))} -> 2015 | R28: =_xlfn.TEXTJOIN(" ", TRUE, B28, C28, D28) -> Volvo XC70 T6 | S28: {=_xlfn.IFS(I28 >= 40, "High", I28>=20, "Medium", I28<20, "Low")} -> High | T28: {=_xlfn.IFS(O28<18200, "Low", O28<=50000, "Medium", O28>50000, "High")} -> Medium
A29: 2015 | B29: Volvo | C29: XC70 | D29: T6 | E29: Wagon | F29: automatic | G29: yv4902nb3f1196951 | H29: ca | I29: 48 | J29: 12725 | K29: beige | L29: beige | M29: volvo na rep/world omni | N29: 32300 | O29: 32500 | P29: Thu Feb 12 2015 04:30:00 GMT-0800 (PST) | Q29: {=VALUE(INDEX(_xlfn.TEXTSPLIT(P29, " "), 4))} -> 2015 | R29: =_xlfn.TEXTJOIN(" ", TRUE, B29, C29, D29) -> Volvo XC70 T6 | S29: {=_xlfn.IFS(I29 >= 40, "High", I29>=20, "Medium", I29<20, "Low")} -> High | T29: {=_xlfn.IFS(O29<18200, "Low", O29<=50000, "Medium", O29>50000, "High")} -> Medium
A30: 2014 | B30: BMW | C30: X5 | D30: sDrive35i | E30: SUV | F30: automatic | G30: 5uxkr2c52e0h33130 | H30: ca | J30: 11278 | K30: gray | L30: black | M30: avis rac/san leandro | N30: 50400 | O30: 34000 | P30: Tue Dec 16 2014 13:00:00 GMT-0800 (PST) | Q30: {=VALUE(INDEX(_xlfn.TEXTSPLIT(P30, " "), 4))} -> 2014 | R30: =_xlfn.TEXTJOIN(" ", TRUE, B30, C30, D30) -> BMW X5 sDrive35i | S30: {=_xlfn.IFS(I30 >= 40, "High", I30>=20, "Medium", I30<20, "Low")} -> Low | T30: {=_xlfn.IFS(O30<18200, "Low", O30<=50000, "Medium", O30>50000, "High")} -> Medium
A31: 2014 | B31: Chevrolet | C31: Camaro | D31: LT | E31: Coupe | F31: automatic | G31: 2g1fb1e35e9238302 | H31: ca | I31: 42 | J31: 11874 | K31: gray | L31: black | M31: midway hfc fleet/ars | N31: 22200 | O31: 19500 | P31: Thu Dec 18 2014 12:00:00 GMT-0800 (PST) | Q31: {=VALUE(INDEX(_xlfn.TEXTSPLIT(P31, " "), 4))} -> 2014 | R31: =_xlfn.TEXTJOIN(" ", TRUE, B31, C31, D31) -> Chevrolet Camaro LT | S31: {=_xlfn.IFS(I31 >= 40, "High", I31>=20, "Medium", I31<20, "Low")} -> High | T31: {=_xlfn.IFS(O31<18200, "Low", O31<=50000, "Medium", O31>50000, "High")} -> Medium
A32: 2014 | B32: Chevrolet | C32: Cruze | D32: 1LT | E32: Sedan | F32: automatic | G32: 1g1pc5sb2e7105471 | H32: ca | I32: 42 | J32: 37888 | K32: gray | L32: black | M32: enterprise vehicle exchange/orange | N32: 11600 | O32: 11500 | P32: Tue Dec 30 2014 12:30:00 GMT-0800 (PST) | Q32: {=VALUE(INDEX(_xlfn.TEXTSPLIT(P32, " "), 4))} -> 2014 | R32: =_xlfn.TEXTJOIN(" ", TRUE, B32, C32, D32) -> Chevrolet Cruze 1LT | S32: {=_xlfn.IFS(I32 >= 40, "High", I32>=20, "Medium", I32<20, "Low")} -> High | T32: {=_xlfn.IFS(O32<18200, "Low", O32<=50000, "Medium", O32>50000, "High")} -> Low
A33: 2014 | B33: Audi | C33: SQ5 | D33: 3.0T Premium Plus quattro | E33: SUV | F33: automatic | G33: wa1cgafp4ea030312 | H33: ca | I33: 42 | J33: 9606 | K33: white | L33: black | M33: audi of downtown l a | N33: 48600 | O33: 47500 | P33: Thu Jan 29 2015 04:00:00 GMT-0800 (PST) | Q33: {=VALUE(INDEX(_xlfn.TEXTSPLIT(P33, " "), 4))} -> 2015 | R33: =_xlfn.TEXTJOIN(" ", TRUE, B33, C33, D33) -> Audi SQ5 3.0T Premium Plus quattro | S33: {=_xlfn.IFS(I33 >= 40, "High", I33>=20, "Medium", I33<20, "Low")} -> High | T33: {=_xlfn.IFS(O33<18200, "Low", O33<=50000, "Medium", O33>50000, "High")} -> Medium
A34: 2015 | B34: Kia | C34: Sorento | D34: LX | E34: SUV | F34: automatic | G34: 5xyktca60fg565226 | H34: ca | I34: 5 | J34: 13757 | K34: red | L34: black | M34: kia motors america inc | N34: 20600 | O34: 20750 | P34: Tue Dec 16 2014 12:30:00 GMT-0800 (PST) | Q34: {=VALUE(INDEX(_xlfn.TEXTSPLIT(P34, " "), 4))} -> 2014 | R34: =_xlfn.TEXTJOIN(" ", TRUE, B34, C34, D34) -> Kia Sorento LX | S34: {=_xlfn.IFS(I34 >= 40, "High", I34>=20, "Medium", I34<20, "Low")} -> Low | T34: {=_xlfn.IFS(O34<18200, "Low", O34<=50000, "Medium", O34>50000, "High")} -> Medium
A35: 2014 | B35: Audi | C35: S5 | D35: Premium Plus quattro | E35: Coupe | F35: automatic | G35: waucgafrxea001689 | H35: ca | I35: 38 | J35: 5875 | K35: black | L35: black | M35: fratelli investment group | N35: 46500 | O35: 44500 | P35: Thu Dec 18 2014 12:00:00 GMT-0800 (PST) | Q35: {=VALUE(INDEX(_xlfn.TEXTSPLIT(P35, " "), 4))} -> 2014 | R35: =_xlfn.TEXTJOIN(" ", TRUE, B35, C35, D35) -> Audi S5 Premium Plus quattro | S35: {=_xlfn.IFS(I35 >= 40, "High", I35>=20, "Medium", I35<20, "Low")} -> Medium | T35: {=_xlfn.IFS(O35<18200, "Low", O35<=50000, "Medium", O35>50000, "High")} -> Medium
A36: 2015 | B36: Kia | C36: Sorento | D36: LX | E36: SUV | F36: automatic | G36: 5xyktca68fg559481 | H36: ca | I36: 44 | J36: 12862 | K36: gray | L36: black | M36: kia motors america inc | N36: 20700 | O36: 21000 | P36: Tue Dec 16 2014 12:30:00 GMT-0800 (PST) | Q36: {=VALUE(INDEX(_xlfn.TEXTSPLIT(P36, " "), 4))} -> 2014 | R36: =_xlfn.TEXTJOIN(" ", TRUE, B36, C36, D36) -> Kia Sorento LX | S36: {=_xlfn.IFS(I36 >= 40, "High", I36>=20, "Medium", I36<20, "Low")} -> High | T36: {=_xlfn.IFS(O36<18200, "Low", O36<=50000, "Medium", O36>50000, "High")} -> Medium
A37: 2014 | B37: Buick | C37: Verano | D37: Convenience Group | E37: Sedan | G37: 1g4pr5sk8e4175320 | H37: ca | I37: 2 | J37: 19531 | K37: gray | L37: gray | M37: enterprise vehicle exchange / tra / rental / tulsa | N37: 15000 | O37: 9200 | P37: Tue Jan 06 2015 04:00:00 GMT-0800 (PST) | Q37: {=VALUE(INDEX(_xlfn.TEXTSPLIT(P37, " "), 4))} -> 2015 | R37: =_xlfn.TEXTJOIN(" ", TRUE, B37, C37, D37) -> Buick Verano Convenience Group | S37: {=_xlfn.IFS(I37 >= 40, "High", I37>=20, "Medium", I37<20, "Low")} -> Low | T37: {=_xlfn.IFS(O37<18200, "Low", O37<=50000, "Medium", O37>50000, "High")} -> Low
A38: 2015 | B38: Chevrolet | C38: Suburban | D38: LTZ | E38: SUV | F38: automatic | G38: 1gnskkkc3fr187901 | H38: ca | I38: 45 | J38: 11426 | K38: black | L38: black | M38: midway hfc fleet/ars | N38: 57300 | O38: 59900 | P38: Thu Dec 18 2014 12:00:00 GMT-0800 (PST) | Q38: {=VALUE(INDEX(_xlfn.TEXTSPLIT(P38, " "), 4))} -> 2014 | R38: =_xlfn.TEXTJOIN(" ", TRUE, B38, C38, D38) -> Chevrolet Suburban LTZ | S38: {=_xlfn.IFS(I38 >= 40, "High", I38>=20, "Medium", I38<20, "Low")} -> High | T38: {=_xlfn.IFS(O38<18200, "Low", O38<=50000, "Medium", O38>50000, "High")} -> High
A39: 2014 | B39: BMW | C39: 3 Series | D39: 328i SULEV | E39: Sedan | F39: automatic | G39: wba3c1c50ek108497 | H39: ca | I39: 5 | J39: 111 | K39: black | L39: â€” | M39: financial services remarketing (lease) | N39: 32200 | O39: 30500 | P39: Thu Jan 15 2015 04:30:00 GMT-0800 (PST) | Q39: {=VALUE(INDEX(_xlfn.TEXTSPLIT(P39, " "), 4))} -> 2015 | R39: =_xlfn.TEXTJOIN(" ", TRUE, B39, C39, D39) -> BMW 3 Series 328i SULEV | S39: {=_xlfn.IFS(I39 >= 40, "High", I39>=20, "Medium", I39<20, "Low")} -> Low | T39: {=_xlfn.IFS(O39<18200, "Low", O39<=50000, "Medium", O39>50000, "High")} -> Medium
A40: 2014 | B40: BMW | C40: M5 | D40: Base | E40: Sedan | F40: automatic | G40: wbsfv9c56ed593069 | H40: ca | I40: 38 | J40: 16360 | K40: black | L40: black | M40: the hertz corporation | N40: 65000 | O40: 64250 | P40: Tue Jan 13 2015 04:30:00 GMT-0800 (PST) | Q40: {=VALUE(INDEX(_xlfn.TEXTSPLIT(P40, " "), 4))} -> 2015 | R40: =_xlfn.TEXTJOIN(" ", TRUE, B40, C40, D40) -> BMW M5 Base | S40: {=_xlfn.IFS(I40 >= 40, "High", I40>=20, "Medium", I40<20, "Low")} -> Medium | T40: {=_xlfn.IFS(O40<18200, "Low", O40<=50000, "Medium", O40>50000, "High")} -> High
A41: 2014 | B41: BMW | C41: 3 Series | D41: 328i SULEV | E41: Sedan | F41: automatic | G41: wba3c1c58ek106688 | H41: ca | I41: 45 | J41: 9027 | K41: white | L41: black | M41: financial services remarketing (lease) | N41: 30200 | O41: 27500 | P41: Thu Jan 15 2015 04:30:00 GMT-0800 (PST) | Q41: {=VALUE(INDEX(_xlfn.TEXTSPLIT(P41, " "), 4))} -> 2015 | R41: =_xlfn.TEXTJOIN(" ", TRUE, B41, C41, D41) -> BMW 3 Series 328i SULEV | S41: {=_xlfn.IFS(I41 >= 40, "High", I41>=20, "Medium", I41<20, "Low")} -> High | T41: {=_xlfn.IFS(O41<18200, "Low", O41<=50000, "Medium", O41>50000, "High")} -> Medium
A42: 2014 | B42: Cadillac | C42: ELR | D42: Base | E42: Coupe | F42: automatic | G42: 1g6rr1e48eu601450 | H42: ca | I42: 47 | J42: 4436 | K42: gray | L42: black | M42: rogue cu | N42: 49400 | O42: 44000 | P42: Wed Feb 04 2015 04:30:00 GMT-0800 (PST) | Q42: {=VALUE(INDEX(_xlfn.TEXTSPLIT(P42, " "), 4))} -> 2015 | R42: =_xlfn.TEXTJOIN(" ", TRUE, B42, C42, D42) -> Cadillac ELR Base | S42: {=_xlfn.IFS(I42 >= 40, "High", I42>=20, "Medium", I42<20, "Low")} -> High | T42: {=_xlfn.IFS(O42<18200, "Low", O42<=50000, "Medium", O42>50000, "High")} -> Medium
A43: 2015 | B43: Hyundai | C43: Sonata | D43: SE | E43: Sedan | F43: automatic | G43: 5npe24af2fh014813 | H43: ca | J43: 9208 | K43: silver | L43: gray | M43: enterprise vehicle exchange / tra / rental / tulsa | N43: 15700 | O43: 10000 | P43: Thu Dec 18 2014 12:00:00 GMT-0800 (PST) | Q43: {=VALUE(INDEX(_xlfn.TEXTSPLIT(P43, " "), 4))} -> 2014 | R43: =_xlfn.TEXTJOIN(" ", TRUE, B43, C43, D43) -> Hyundai Sonata SE | S43: {=_xlfn.IFS(I43 >= 40, "High", I43>=20, "Medium", I43<20, "Low")} -> Low | T43: {=_xlfn.IFS(O43<18200, "Low", O43<=50000, "Medium", O43>50000, "High")} -> Low
A44: 2014 | B44: BMW | C44: 6 Series | D44: 650i | E44: Convertible | F44: automatic | G44: wbayp9c50ed169281 | H44: ca | I44: 32 | J44: 13205 | K44: white | L44: black | M44: the hertz corporation | N44: 66000 | O44: 65000 | P44: Tue Jan 06 2015 04:30:00 GMT-0800 (PST) | Q44: {=VALUE(INDEX(_xlfn.TEXTSPLIT(P44, " "), 4))} -> 2015 | R44: =_xlfn.TEXTJOIN(" ", TRUE, B44, C44, D44) -> BMW 6 Series 650i | S44: {=_xlfn.IFS(I44 >= 40, "High", I44>=20, "Medium", I44<20, "Low")} -> Medium | T44: {=_xlfn.IFS(O44<18200, "Low", O44<=50000, "Medium", O44>50000, "High")} -> High
A45: 2015 | B45: Volvo | C45: V60 | D45: T5 | E45: Wagon | F45: automatic | G45: yv1612sb9f1202043 | H45: ca | I45: 41 | J45: 11846 | K45: white | L45: beige | M45: volvo na rep/world omni | N45: 31300 | O45: 30000 | P45: Thu Dec 18 2014 12:30:00 GMT-0800 (PST) | Q45: {=VALUE(INDEX(_xlfn.TEXTSPLIT(P45, " "), 4))} -> 2014 | R45: =_xlfn.TEXTJOIN(" ", TRUE, B45, C45, D45) -> Volvo V60 T5 | S45: {=_xlfn.IFS(I45 >= 40, "High", I45>=20, "Medium", I45<20, "Low")} -> High | T45: {=_xlfn.IFS(O45<18200, "Low", O45<=50000, "Medium", O45>50000, "High")} -> Medium
A46: 2014 | B46: Chevrolet | C46: Cruze | D46: 1LT | E46: Sedan | G46: 1g1pc5sb6e7128803 | H46: ca | J46: 38261 | K46: white | L46: â€” | M46: avis tra | N46: 11450 | O46: 2000 | P46: Tue Dec 16 2014 13:00:00 GMT-0800 (PST) | Q46: {=VALUE(INDEX(_xlfn.TEXTSPLIT(P46, " "), 4))} -> 2014 | R46: =_xlfn.TEXTJOIN(" ", TRUE, B46, C46, D46) -> Chevrolet Cruze 1LT | S46: {=_xlfn.IFS(I46 >= 40, "High", I46>=20, "Medium", I46<20, "Low")} -> Low | T46: {=_xlfn.IFS(O46<18200, "Low", O46<=50000, "Medium", O46>50000, "High")} -> Low
A47: 2014 | B47: BMW | C47: X6 | D47: xDrive35i | E47: SUV | F47: automatic | G47: 5uxfg2c53e0h11080 | H47: ca | I47: 4 | J47: 379 | K47: white | L47: black | M47: financial services remarketing (lease) | N47: 54800 | O47: 51700 | P47: Thu Dec 18 2014 12:30:00 GMT-0800 (PST) | Q47: {=VALUE(INDEX(_xlfn.TEXTSPLIT(P47, " "), 4))} -> 2014 | R47: =_xlfn.TEXTJOIN(" ", TRUE, B47, C47, D47) -> BMW X6 xDrive35i | S47: {=_xlfn.IFS(I47 >= 40, "High", I47>=20, "Medium", I47<20, "Low")} -> Low | T47: {=_xlfn.IFS(O47<18200, "Low", O47<=50000, "Medium", O47>50000, "High")} -> High
A48: 2015 | B48: Volvo | C48: V60 | D48: T5 | E48: Wagon | F48: automatic | G48: yv1612sb1f1201503 | H48: ca | I48: 42 | J48: 12242 | K48: black | L48: gray | M48: volvo na rep/world omni | N48: 31200 | O48: 30000 | P48: Thu Dec 18 2014 12:30:00 GMT-0800 (PST) | Q48: {=VALUE(INDEX(_xlfn.TEXTSPLIT(P48, " "), 4))} -> 2014 | R48: =_xlfn.TEXTJOIN(" ", TRUE, B48, C48, D48) -> Volvo V60 T5 | S48: {=_xlfn.IFS(I48 >= 40, "High", I48>=20, "Medium", I48<20, "Low")} -> High | T48: {=_xlfn.IFS(O48<18200, "Low", O48<=50000, "Medium", O48>50000, "High")} -> Medium
A49: 2014 | B49: Chevrolet | C49: Cruze | D49: 2LT | E49: Sedan | F49: automatic | G49: 1g1pe5sb6e7118217 | H49: ca | I49: 34 | J49: 40661 | K49: silver | L49: black | M49: avis corporation | N49: 13050 | O49: 13000 | P49: Thu Jan 22 2015 03:30:00 GMT-0800 (PST) | Q49: {=VALUE(INDEX(_xlfn.TEXTSPLIT(P49, " "), 4))} -> 2015 | R49: =_xlfn.TEXTJOIN(" ", TRUE, B49, C49, D49) -> Chevrolet Cruze 2LT | S49: {=_xlfn.IFS(I49 >= 40, "High", I49>=20, "Medium", I49<20, "Low")} -> Medium | T49: {=_xlfn.IFS(O49<18200, "Low", O49<=50000, "Medium", O49>50000, "High")} -> Low
A50: 2014 | B50: Acura | C50: ILX | D50: Technology Package | E50: Sedan | F50: automatic | G50: 19vde1f70ee008913 | H50: ca | I50: 25 | J50: 9051 | K50: gray | L50: black | M50: american honda motor company | N50: 22700 | O50: 21250 | P50: Thu Dec 18 2014 12:00:00 GMT-0800 (PST) | Q50: {=VALUE(INDEX(_xlfn.TEXTSPLIT(P50, " "), 4))} -> 2014 | R50: =_xlfn.TEXTJOIN(" ", TRUE, B50, C50, D50) -> Acura ILX Technology Package | S50: {=_xlfn.IFS(I50 >= 40, "High", I50>=20, "Medium", I50<20, "Low")} -> Medium | T50: {=_xlfn.IFS(O50<18200, "Low", O50<=50000, "Medium", O50>50000, "High")} -> Medium
A51: 2015 | B51: Kia | C51: Sorento | D51: LX | E51: SUV | F51: automatic | G51: 5xyktca67fg570973 | H51: ca | I51: 5 | J51: 13878 | K51: silver | L51: black | M51: kia motors america inc | N51: 20600 | O51: 20750 | P51: Tue Dec 16 2014 12:30:00 GMT-0800 (PST) | Q51: {=VALUE(INDEX(_xlfn.TEXTSPLIT(P51, " "), 4))} -> 2014 | R51: =_xlfn.TEXTJOIN(" ", TRUE, B51, C51, D51) -> Kia Sorento LX | S51: {=_xlfn.IFS(I51 >= 40, "High", I51>=20, "Medium", I51<20, "Low")} -> Low | T51: {=_xlfn.IFS(O51<18200, "Low", O51<=50000, "Medium", O51>50000, "High")} -> Medium
A52: 2015 | B52: Volvo | C52: V60 | D52: T5 | E52: Wagon | F52: automatic | G52: yv1612sbxf1202276 | H52: ca | I52: 37 | J52: 10906 | K52: silver | L52: black | M52: volvo na rep/world omni | N52: 31500 | O52: 30000 | P52: Thu Dec 18 2014 12:30:00 GMT-0800 (PST) | Q52: {=VALUE(INDEX(_xlfn.TEXTSPLIT(P52, " "), 4))} -> 2014 | R52: =_xlfn.TEXTJOIN(" ", TRUE, B52, C52, D52) -> Volvo V60 T5 | S52: {=_xlfn.IFS(I52 >= 40, "High", I52>=20, "Medium", I52<20, "Low")} -> Medium | T52: {=_xlfn.IFS(O52<18200, "Low", O52<=50000, "Medium", O52>50000, "High")} -> Medium
A53: 2015 | B53: Nissan | C53: Altima | D53: 2.5 S | E53: Sedan | F53: automatic | G53: 1n4al3ap4fn313644 | H53: ca | J53: 10678 | K53: gray | L53: black | M53: enterprise vehicle exchange / tra / rental / tulsa | N53: 15150 | O53: 11600 | P53: Thu Dec 18 2014 12:00:00 GMT-0800 (PST) | Q53: {=VALUE(INDEX(_xlfn.TEXTSPLIT(P53, " "), 4))} -> 2014 | R53: =_xlfn.TEXTJOIN(" ", TRUE, B53, C53, D53) -> Nissan Altima 2.5 S | S53: {=_xlfn.IFS(I53 >= 40, "High", I53>=20, "Medium", I53<20, "Low")} -> Low | T53: {=_xlfn.IFS(O53<18200, "Low", O53<=50000, "Medium", O53>50000, "High")} -> Low
A54: 2014 | B54: BMW | C54: 6 Series Gran Coupe | D54: 650i | E54: Sedan | F54: automatic | G54: wba6b2c51ed129563 | H54: ca | I54: 42 | J54: 7305 | K54: white | L54: black | M54: the hertz corporation | N54: 65000 | O54: 66100 | P54: Wed Dec 17 2014 12:30:00 GMT-0800 (PST) | Q54: {=VALUE(INDEX(_xlfn.TEXTSPLIT(P54, " "), 4))} -> 2014 | R54: =_xlfn.TEXTJOIN(" ", TRUE, B54, C54, D54) -> BMW 6 Series Gran Coupe 650i | S54: {=_xlfn.IFS(I54 >= 40, "High", I54>=20, "Medium", I54<20, "Low")} -> High | T54: {=_xlfn.IFS(O54<18200, "Low", O54<=50000, "Medium", O54>50000, "High")} -> High
A55: 2015 | B55: Nissan | C55: Altima | D55: 2.5 S | E55: Sedan | F55: automatic | G55: 1n4al3ap1fn331213 | H55: ca | I55: 1 | J55: 4314 | K55: black | L55: black | M55: enterprise vehicle exchange / tra / rental / tulsa | N55: 15500 | O55: 11500 | P55: Tue Dec 30 2014 12:00:00 GMT-0800 (PST) | Q55: {=VALUE(INDEX(_xlfn.TEXTSPLIT(P55, " "), 4))} -> 2014 | R55: =_xlfn.TEXTJOIN(" ", TRUE, B55, C55, D55) -> Nissan Altima 2.5 S | S55: {=_xlfn.IFS(I55 >= 40, "High", I55>=20, "Medium", I55<20, "Low")} -> Low | T55: {=_xlfn.IFS(O55<18200, "Low", O55<=50000, "Medium", O55>50000, "High")} -> Low
A56: 2015 | B56: Kia | C56: K900 | D56: Luxury | E56: Sedan | F56: automatic | G56: knalw4d42f6019667 | H56: ca | I56: 42 | J56: 5304 | K56: blue | L56: black | M56: kia motors america inc | N56: 39500 | O56: 40000 | P56: Tue Feb 17 2015 04:30:00 GMT-0800 (PST) | Q56: {=VALUE(INDEX(_xlfn.TEXTSPLIT(P56, " "), 4))} -> 2015 | R56: =_xlfn.TEXTJOIN(" ", TRUE, B56, C56, D56) -> Kia K900 Luxury | S56: {=_xlfn.IFS(I56 >= 40, "High", I56>=20, "Medium", I56<20, "Low")} -> High | T56: {=_xlfn.IFS(O56<18200, "Low", O56<=50000, "Medium", O56>50000, "High")} -> Medium
A57: 2015 | B57: Kia | C57: Sorento | D57: LX | E57: SUV | F57: automatic | G57: 5xyktca63fg570727 | H57: ca | I57: 48 | J57: 10357 | K57: silver | L57: gray | M57: kia motors america inc | N57: 20700 | O57: 20500 | P57: Tue Dec 16 2014 12:30:00 GMT-0800 (PST) | Q57: {=VALUE(INDEX(_xlfn.TEXTSPLIT(P57, " "), 4))} -> 2014 | R57: =_xlfn.TEXTJOIN(" ", TRUE, B57, C57, D57) -> Kia Sorento LX | S57: {=_xlfn.IFS(I57 >= 40, "High", I57>=20, "Medium", I57<20, "Low")} -> High | T57: {=_xlfn.IFS(O57<18200, "Low", O57<=50000, "Medium", O57>50000, "High")} -> Medium
A58: 2015 | B58: Chevrolet | C58: Malibu | D58: LT | E58: Sedan | F58: automatic | G58: 1g11d5sl6fu106427 | H58: ca | I58: 1 | J58: 6105 | K58: silver | L58: black | M58: enterprise vehicle exchange / tra / rental / tulsa | N58: 16600 | O58: 9800 | P58: Wed Jan 14 2015 07:05:00 GMT-0800 (PST) | Q58: {=VALUE(INDEX(_xlfn.TEXTSPLIT(P58, " "), 4))} -> 2015 | R58: =_xlfn.TEXTJOIN(" ", TRUE, B58, C58, D58) -> Chevrolet Malibu LT | S58: {=_xlfn.IFS(I58 >= 40, "High", I58>=20, "Medium", I58<20, "Low")} -> Low | T58: {=_xlfn.IFS(O58<18200, "Low", O58<=50000, "Medium", O58>50000, "High")} -> Low
A59: 2015 | B59: Lexus | C59: RX 350 | D59: Base | E59: SUV | F59: automatic | G59: 2t2zk1ba7fc155782 | H59: ca | I59: 43 | J59: 7770 | K59: white | L59: black | M59: lexus financial services | N59: 41200 | O59: 38400 | P59: Tue Dec 30 2014 00:00:00 GMT-0800 (PST) | Q59: {=VALUE(INDEX(_xlfn.TEXTSPLIT(P59, " "), 4))} -> 2014 | R59: =_xlfn.TEXTJOIN(" ", TRUE, B59, C59, D59) -> Lexus RX 350 Base | S59: {=_xlfn.IFS(I59 >= 40, "High", I59>=20, "Medium", I59<20, "Low")} -> High | T59: {=_xlfn.IFS(O59<18200, "Low", O59<=50000, "Medium", O59>50000, "High")} -> Medium
A60: 2015 | B60: Kia | C60: Sorento | D60: LX | E60: SUV | F60: automatic | G60: 5xykt3a62fg579841 | H60: ca | I60: 5 | J60: 5214 | K60: white | L60: black | M60: kia motors finance | N60: 19400 | O60: 19300 | P60: Tue Dec 16 2014 12:00:00 GMT-0800 (PST) | Q60: {=VALUE(INDEX(_xlfn.TEXTSPLIT(P60, " "), 4))} -> 2014 | R60: =_xlfn.TEXTJOIN(" ", TRUE, B60, C60, D60) -> Kia Sorento LX | S60: {=_xlfn.IFS(I60 >= 40, "High", I60>=20, "Medium", I60<20, "Low")} -> Low | T60: {=_xlfn.IFS(O60<18200, "Low", O60<=50000, "Medium", O60>50000, "High")} -> Medium
A61: 2014 | B61: BMW | C61: M5 | D61: Base | E61: Sedan | F61: automatic | G61: wbsfv9c51ed097712 | H61: ca | I61: 47 | J61: 7766 | K61: gray | L61: black | M61: fratelli investment group | N61: 71000 | O61: 77250 | P61: Thu Dec 18 2014 12:00:00 GMT-0800 (PST) | Q61: {=VALUE(INDEX(_xlfn.TEXTSPLIT(P61, " "), 4))} -> 2014 | R61: =_xlfn.TEXTJOIN(" ", TRUE, B61, C61, D61) -> BMW M5 Base | S61: {=_xlfn.IFS(I61 >= 40, "High", I61>=20, "Medium", I61<20, "Low")} -> High | T61: {=_xlfn.IFS(O61<18200, "Low", O61<=50000, "Medium", O61>50000, "High")} -> High
A62: 2015 | B62: Kia | C62: K900 | D62: Luxury | E62: Sedan | F62: automatic | G62: knalw4d42f6018633 | H62: ca | I62: 44 | J62: 9684 | K62: white | L62: gray | M62: kia motors america inc | N62: 41000 | O62: 41000 | P62: Tue Jan 20 2015 04:30:00 GMT-0800 (PST) | Q62: {=VALUE(INDEX(_xlfn.TEXTSPLIT(P62, " "), 4))} -> 2015 | R62: =_xlfn.TEXTJOIN(" ", TRUE, B62, C62, D62) -> Kia K900 Luxury | S62: {=_xlfn.IFS(I62 >= 40, "High", I62>=20, "Medium", I62<20, "Low")} -> High | T62: {=_xlfn.IFS(O62<18200, "Low", O62<=50000, "Medium", O62>50000, "High")} -> Medium
A63: 2015 | B63: Audi | C63: A3 | D63: 1.8 TFSI Premium | E63: Sedan | F63: automatic | G63: wauacgff6f1029938 | H63: ca | I63: 2 | J63: 31 | K63: white | L63: black | M63: enterprise vehicle exchange / tra / rental / tulsa | N63: 24200 | O63: 17300 | P63: Tue Dec 23 2014 12:00:00 GMT-0800 (PST) | Q63: {=VALUE(INDEX(_xlfn.TEXTSPLIT(P63, " "), 4))} -> 2014 | R63: =_xlfn.TEXTJOIN(" ", TRUE, B63, C63, D63) -> Audi A3 1.8 TFSI Premium | S63: {=_xlfn.IFS(I63 >= 40, "High", I63>=20, "Medium", I63<20, "Low")} -> Low | T63: {=_xlfn.IFS(O63<18200, "Low", O63<=50000, "Medium", O63>50000, "High")} -> Low
A64: 2015 | B64: Nissan | C64: Versa | D64: 1.6 SL | E64: Sedan | F64: manual | G64: 3n1cn7ap7fl842707 | H64: ca | I64: 39 | J64: 1608 | K64: purple | L64: black | M64: nissan-infiniti lt | N64: 10900 | O64: 11000 | P64: Wed Dec 17 2014 12:30:00 GMT-0800 (PST) | Q64: {=VALUE(INDEX(_xlfn.TEXTSPLIT(P64, " "), 4))} -> 2014 | R64: =_xlfn.TEXTJOIN(" ", TRUE, B64, C64, D64) -> Nissan Versa 1.6 SL | S64: {=_xlfn.IFS(I64 >= 40, "High", I64>=20, "Medium", I64<20, "Low")} -> Medium | T64: {=_xlfn.IFS(O64<18200, "Low", O64<=50000, "Medium", O64>50000, "High")} -> Low
A65: 2014 | B65: Chevrolet | C65: Camaro | D65: LT | E65: Coupe | F65: automatic | G65: 2g1fb1e35e9238493 | H65: ca | I65: 31 | J65: 9914 | K65: black | L65: black | M65: midway hfc fleet/ars | N65: 22500 | O65: 20600 | P65: Thu Dec 18 2014 12:00:00 GMT-0800 (PST) | Q65: {=VALUE(INDEX(_xlfn.TEXTSPLIT(P65, " "), 4))} -> 2014 | R65: =_xlfn.TEXTJOIN(" ", TRUE, B65, C65, D65) -> Chevrolet Camaro LT | S65: {=_xlfn.IFS(I65 >= 40, "High", I65>=20, "Medium", I65<20, "Low")} -> Medium | T65: {=_xlfn.IFS(O65<18200, "Low", O65<=50000, "Medium", O65>50000, "High")} -> Medium
... A73: 2014 | B73: BMW | C73: X1 | D73: sDrive28i | E73: SUV | F73: automatic | G73: wbavm1c53evw47779 | H73: ca | I73: 48 | J73: 19689 | K73: white | L73: black | M73: financial services remarketing (lease) | N73: 23700 | O73: 26500 | P73: Thu Dec 18 2014 12:30:00 GMT-0800 (PST) | Q73: {=VALUE(INDEX(_xlfn.TEXTSPLIT(P73, " "), 4))} -> 2014 | R73: =_xlfn.TEXTJOIN(" ", TRUE, B73, C73, D73) -> BMW X1 sDrive28i | S73: {=_xlfn.IFS(I73 >= 40, "High", I73>=20, "Medium", I73<20, "Low")} -> High | T73: {=_xlfn.IFS(O73<18200, "Low", O73<=50000, "Medium", O73>50000, "High")} -> Medium
A74: 2014 | B74: BMW | D74: 750Li | E74: Sedan | F74: automatic | G74: wbaye8c59ed134514 | H74: ca | I74: 43 | J74: 12172 | K74: black | L74: black | M74: financial services remarketing (lease) | N74: 67000 | O74: 66000 | P74: Thu Dec 18 2014 12:30:00 GMT-0800 (PST) | Q74: {=VALUE(INDEX(_xlfn.TEXTSPLIT(P74, " "), 4))} -> 2014 | R74: =_xlfn.TEXTJOIN(" ", TRUE, B74, C74, D74) -> BMW 750Li | S74: {=_xlfn.IFS(I74 >= 40, "High", I74>=20, "Medium", I74<20, "Low")} -> High | T74: {=_xlfn.IFS(O74<18200, "Low", O74<=50000, "Medium", O74>50000, "High")} -> High
A75: 2014 | B75: Chevrolet | C75: Camaro | D75: LT | E75: Coupe | F75: automatic | G75: 2g1fb1e31e9248986 | H75: ca | I75: 1 | J75: 20595 | K75: red | L75: gray | M75: enterprise vehicle exchange / tra / rental / tulsa | N75: 20800 | O75: 13600 | P75: Tue Dec 16 2014 13:00:00 GMT-0800 (PST) | Q75: {=VALUE(INDEX(_xlfn.TEXTSPLIT(P75, " "), 4))} -> 2014 | R75: =_xlfn.TEXTJOIN(" ", TRUE, B75, C75, D75) -> Chevrolet Camaro LT | S75: {=_xlfn.IFS(I75 >= 40, "High", I75>=20, "Medium", I75<20, "Low")} -> Low | T75: {=_xlfn.IFS(O75<18200, "Low", O75<=50000, "Medium", O75>50000, "High")} -> Low
A76: 2015 | B76: Volvo | C76: V60 | D76: T5 | E76: Wagon | F76: automatic | G76: yv1612sb8f1201529 | H76: ca | I76: 4 | J76: 13623 | K76: silver | L76: black | M76: volvo na rep/world omni | N76: 28400 | O76: 28000 | P76: Thu Feb 26 2015 04:30:00 GMT-0800 (PST) | Q76: {=VALUE(INDEX(_xlfn.TEXTSPLIT(P76, " "), 4))} -> 2015 | R76: =_xlfn.TEXTJOIN(" ", TRUE, B76, C76, D76) -> Volvo V60 T5 | S76: {=_xlfn.IFS(I76 >= 40, "High", I76>=20, "Medium", I76<20, "Low")} -> Low | T76: {=_xlfn.IFS(O76<18200, "Low", O76<=50000, "Medium", O76>50000, "High")} -> Medium
A77: 2014 | B77: BMW | C77: 6 Series | D77: 650i | E77: Coupe | F77: automatic | G77: wbaym9c53ed248064 | H77: ca | I77: 4 | J77: 9837 | K77: black | L77: â€” | M77: financial services remarketing (lease) | N77: 62000 | O77: 61500 | P77: Thu Dec 18 2014 12:30:00 GMT-0800 (PST) | Q77: {=VALUE(INDEX(_xlfn.TEXTSPLIT(P77, " "), 4))} -> 2014 | R77: =_xlfn.TEXTJOIN(" ", TRUE, B77, C77, D77) -> BMW 6 Series 650i | S77: {=_xlfn.IFS(I77 >= 40, "High", I77>=20, "Medium", I77<20, "Low")} -> Low | T77: {=_xlfn.IFS(O77<18200, "Low", O77<=50000, "Medium", O77>50000, "High")} -> High
A78: 2014 | B78: Chevrolet | C78: Camaro | D78: LT | E78: Coupe | F78: automatic | G78: 2g1fb1e37e9270877 | H78: ca | I78: 3 | J78: 13606 | K78: black | L78: black | M78: enterprise vehicle exchange / tra / rental / tulsa | N78: 21400 | O78: 13000 | P78: Tue Jan 06 2015 13:00:00 GMT-0800 (PST) | Q78: {=VALUE(INDEX(_xlfn.TEXTSPLIT(P78, " "), 4))} -> 2015 | R78: =_xlfn.TEXTJOIN(" ", TRUE, B78, C78, D78) -> Chevrolet Camaro LT | S78: {=_xlfn.IFS(I78 >= 40, "High", I78>=20, "Medium", I78<20, "Low")} -> Low | T78: {=_xlfn.IFS(O78<18200, "Low", O78<=50000, "Medium", O78>50000, "High")} -> Low
A79: 2014 | B79: BMW | C79: 6 Series Gran Coupe | D79: 650i | E79: Sedan | F79: automatic | G79: wba6b2c53ed128866 | H79: ca | I79: 29 | J79: 37752 | K79: white | L79: black | M79: financial services remarketing (lease) | N79: 62000 | O79: 58000 | P79: Tue Dec 16 2014 12:30:00 GMT-0800 (PST) | Q79: {=VALUE(INDEX(_xlfn.TEXTSPLIT(P79, " "), 4))} -> 2014 | R79: =_xlfn.TEXTJOIN(" ", TRUE, B79, C79, D79) -> BMW 6 Series Gran Coupe 650i | S79: {=_xlfn.IFS(I79 >= 40, "High", I79>=20, "Medium", I79<20, "Low")} -> Medium | T79: {=_xlfn.IFS(O79<18200, "Low", O79<=50000, "Medium", O79>50000, "High")} -> High
A80: 2015 | B80: Kia | C80: Sorento | D80: LX | E80: SUV | F80: automatic | G80: 5xyktca68fg570979 | H80: ca | I80: 44 | J80: 9161 | K80: silver | L80: black | M80: kia motors america inc | N80: 20800 | O80: 22250 | P80: Tue Dec 16 2014 12:30:00 GMT-0800 (PST) | Q80: {=VALUE(INDEX(_xlfn.TEXTSPLIT(P80, " "), 4))} -> 2014 | R80: =_xlfn.TEXTJOIN(" ", TRUE, B80, C80, D80) -> Kia Sorento LX | S80: {=_xlfn.IFS(I80 >= 40, "High", I80>=20, "Medium", I80<20, "Low")} -> High | T80: {=_xlfn.IFS(O80<18200, "Low", O80<=50000, "Medium", O80>50000, "High")} -> Medium
A81: 2015 | B81: Kia | C81: Sorento | D81: LX | E81: SUV | F81: automatic | G81: 5xyktca65fg571619 | H81: ca | I81: 5 | J81: 11001 | K81: white | L81: black | M81: kia motors america inc | N81: 20700 | O81: 22500 | P81: Tue Dec 16 2014 12:30:00 GMT-0800 (PST) | Q81: {=VALUE(INDEX(_xlfn.TEXTSPLIT(P81, " "), 4))} -> 2014 | R81: =_xlfn.TEXTJOIN(" ", TRUE, B81, C81, D81) -> Kia Sorento LX | S81: {=_xlfn.IFS(I81 >= 40, "High", I81>=20, "Medium", I81<20, "Low")} -> Low | T81: {=_xlfn.IFS(O81<18200, "Low", O81<=50000, "Medium", O81>50000, "High")} -> Medium
A82: 2014 | B82: Buick | C82: Enclave | D82: Leather Group | E82: SUV | F82: automatic | G82: 5gakrbkd2ej294045 | H82: ca | I82: 1 | J82: 14599 | K82: gray | L82: black | M82: enterprise vehicle exchange / tra / rental / tulsa | N82: 31000 | O82: 24100 | P82: Tue Dec 30 2014 12:00:00 GMT-0800 (PST) | Q82: {=VALUE(INDEX(_xlfn.TEXTSPLIT(P82, " "), 4))} -> 2014 | R82: =_xlfn.TEXTJOIN(" ", TRUE, B82, C82, D82) -> Buick Enclave Leather Group | S82: {=_xlfn.IFS(I82 >= 40, "High", I82>=20, "Medium", I82<20, "Low")} -> Low | T82: {=_xlfn.IFS(O82<18200, "Low", O82<=50000, "Medium", O82>50000, "High")} -> Medium
A83: 2014 | B83: BMW | C83: M5 | D83: Base | E83: Sedan | F83: automatic | G83: wbsfv9c54ed593085 | H83: ca | I83: 38 | J83: 13386 | K83: white | L83: black | M83: the hertz corporation | N83: 67000 | O83: 65000 | P83: Thu Dec 18 2014 12:30:00 GMT-0800 (PST) | Q83: {=VALUE(INDEX(_xlfn.TEXTSPLIT(P83, " "), 4))} -> 2014 | R83: =_xlfn.TEXTJOIN(" ", TRUE, B83, C83, D83) -> BMW M5 Base | S83: {=_xlfn.IFS(I83 >= 40, "High", I83>=20, "Medium", I83<20, "Low")} -> Medium | T83: {=_xlfn.IFS(O83<18200, "Low", O83<=50000, "Medium", O83>50000, "High")} -> High
A84: 2014 | B84: BMW | C84: M5 | D84: Base | E84: Sedan | F84: automatic | G84: wbsfv9c55ed593080 | H84: ca | I84: 41 | J84: 15161 | K84: white | L84: black | M84: the hertz corporation | N84: 66000 | O84: 65801 | P84: Tue Dec 23 2014 12:30:00 GMT-0800 (PST) | Q84: {=VALUE(INDEX(_xlfn.TEXTSPLIT(P84, " "), 4))} -> 2014 | R84: =_xlfn.TEXTJOIN(" ", TRUE, B84, C84, D84) -> BMW M5 Base | S84: {=_xlfn.IFS(I84 >= 40, "High", I84>=20, "Medium", I84<20, "Low")} -> High | T84: {=_xlfn.IFS(O84<18200, "Low", O84<=50000, "Medium", O84>50000, "High")} -> High
A85: 2014 | B85: Audi | C85: TTS | D85: quattro | E85: Coupe | F85: automatic | G85: trub1afk9e1007640 | H85: ca | I85: 28 | J85: 3996 | K85: silver | L85: black | M85: fratelli investment group | N85: 41400 | O85: 34250 | P85: Thu Dec 18 2014 12:00:00 GMT-0800 (PST) | Q85: {=VALUE(INDEX(_xlfn.TEXTSPLIT(P85, " "), 4))} -> 2014 | R85: =_xlfn.TEXTJOIN(" ", TRUE, B85, C85, D85) -> Audi TTS quattro | S85: {=_xlfn.IFS(I85 >= 40, "High", I85>=20, "Medium", I85<20, "Low")} -> Medium | T85: {=_xlfn.IFS(O85<18200, "Low", O85<=50000, "Medium", O85>50000, "High")} -> Medium
A86: 2015 | B86: Hyundai | C86: Elantra | D86: SE | E86: Sedan | F86: automatic | G86: 5npdh4ae2fh566023 | H86: ca | I86: 2 | J86: 10551 | K86: red | L86: gray | M86: enterprise vehicle exchange / tra / rental / tulsa | N86: 13850 | O86: 10600 | P86: Tue Jan 13 2015 13:00:00 GMT-0800 (PST) | Q86: {=VALUE(INDEX(_xlfn.TEXTSPLIT(P86, " "), 4))} -> 2015 | R86: =_xlfn.TEXTJOIN(" ", TRUE, B86, C86, D86) -> Hyundai Elantra SE | S86: {=_xlfn.IFS(I86 >= 40, "High", I86>=20, "Medium", I86<20, "Low")} -> Low | T86: {=_xlfn.IFS(O86<18200, "Low", O86<=50000, "Medium", O86>50000, "High")} -> Low
... A90: 2014 | B90: Chevrolet | C90: Cruze | D90: 2LT | E90: Sedan | F90: automatic | G90: 1g1pe5sb0e7134820 | H90: ca | I90: 42 | J90: 39623 | K90: blue | L90: black | M90: avis corporation | N90: 13350 | O90: 13200 | P90: Thu Jan 15 2015 03:30:00 GMT-0800 (PST) | Q90: {=VALUE(INDEX(_xlfn.TEXTSPLIT(P90, " "), 4))} -> 2015 | R90: =_xlfn.TEXTJOIN(" ", TRUE, B90, C90, D90) -> Chevrolet Cruze 2LT | S90: {=_xlfn.IFS(I90 >= 40, "High", I90>=20, "Medium", I90<20, "Low")} -> High | T90: {=_xlfn.IFS(O90<18200, "Low", O90<=50000, "Medium", O90>50000, "High")} -> Low
A91: 2014 | B91: Chevrolet | C91: Silverado 2500HD | D91: Work Truck | E91: Crew Cab | G91: 1gc1kvc84ef152736 | H91: ca | I91: 36 | J91: 8742 | K91: white | L91: gray | M91: enterprise fleet management exchange inc. | N91: 34000 | O91: 34000 | P91: Thu Dec 18 2014 11:30:00 GMT-0800 (PST) | Q91: {=VALUE(INDEX(_xlfn.TEXTSPLIT(P91, " "), 4))} -> 2014 | R91: =_xlfn.TEXTJOIN(" ", TRUE, B91, C91, D91) -> Chevrolet Silverado 2500HD Work Truck | S91: {=_xlfn.IFS(I91 >= 40, "High", I91>=20, "Medium", I91<20, "Low")} -> Medium | T91: {=_xlfn.IFS(O91<18200, "Low", O91<=50000, "Medium", O91>50000, "High")} -> Medium
A92: 2015 | B92: Kia | C92: Sorento | D92: LX | E92: SUV | F92: automatic | G92: 5xyktca60fg563086 | H92: ca | I92: 5 | J92: 16348 | K92: gray | L92: gray | M92: kia motors america inc | N92: 20500 | O92: 20500 | P92: Tue Dec 16 2014 12:30:00 GMT-0800 (PST) | Q92: {=VALUE(INDEX(_xlfn.TEXTSPLIT(P92, " "), 4))} -> 2014 | R92: =_xlfn.TEXTJOIN(" ", TRUE, B92, C92, D92) -> Kia Sorento LX | S92: {=_xlfn.IFS(I92 >= 40, "High", I92>=20, "Medium", I92<20, "Low")} -> Low | T92: {=_xlfn.IFS(O92<18200, "Low", O92<=50000, "Medium", O92>50000, "High")} -> Medium
A93: 2015 | B93: Hyundai | C93: Elantra | D93: SE | E93: Sedan | F93: automatic | G93: 5npdh4ae2fh553630 | H93: ca | J93: 9750 | K93: blue | L93: gray | M93: avis rac/san leandro | N93: 13700 | O93: 10000 | P93: Tue Dec 16 2014 12:00:00 GMT-0800 (PST) | Q93: {=VALUE(INDEX(_xlfn.TEXTSPLIT(P93, " "), 4))} -> 2014 | R93: =_xlfn.TEXTJOIN(" ", TRUE, B93, C93, D93) -> Hyundai Elantra SE | S93: {=_xlfn.IFS(I93 >= 40, "High", I93>=20, "Medium", I93<20, "Low")} -> Low | T93: {=_xlfn.IFS(O93<18200, "Low", O93<=50000, "Medium", O93>50000, "High")} -> Low
A94: 2015 | B94: Hyundai | C94: Elantra | D94: SE | E94: Sedan | F94: automatic | G94: 5npdh4ae4fh552981 | H94: ca | I94: 35 | J94: 3367 | K94: silver | L94: gray | M94: ag leaseplan | N94: 13900 | O94: 13200 | P94: Wed Dec 17 2014 12:30:00 GMT-0800 (PST) | Q94: {=VALUE(INDEX(_xlfn.TEXTSPLIT(P94, " "), 4))} -> 2014 | R94: =_xlfn.TEXTJOIN(" ", TRUE, B94, C94, D94) -> Hyundai Elantra SE | S94: {=_xlfn.IFS(I94 >= 40, "High", I94>=20, "Medium", I94<20, "Low")} -> Medium | T94: {=_xlfn.IFS(O94<18200, "Low", O94<=50000, "Medium", O94>50000, "High")} -> Low
A95: 2014 | B95: Acura | C95: MDX | D95: Advance and Entertainment Packages | E95: SUV | F95: automatic | G95: 5fryd3h83eb011004 | H95: ca | I95: 49 | J95: 21523 | K95: white | L95: gray | M95: onemain rem/m&m auto traders | N95: 39500 | O95: 41500 | P95: Thu Dec 18 2014 12:00:00 GMT-0800 (PST) | Q95: {=VALUE(INDEX(_xlfn.TEXTSPLIT(P95, " "), 4))} -> 2014 | R95: =_xlfn.TEXTJOIN(" ", TRUE, B95, C95, D95) -> Acura MDX Advance and Entertainment Packages | S95: {=_xlfn.IFS(I95 >= 40, "High", I95>=20, "Medium", I95<20, "Low")} -> High | T95: {=_xlfn.IFS(O95<18200, "Low", O95<=50000, "Medium", O95>50000, "High")} -> Medium
A96: 2015 | B96: Ford | C96: Fusion | D96: SE | E96: Sedan | F96: automatic | G96: 3fa6p0h7xfr151689 | H96: ca | I96: 1 | J96: 4205 | K96: white | L96: black | M96: enterprise vehicle exchange / tra / rental / tulsa | N96: 14700 | O96: 12000 | P96: Wed Dec 17 2014 15:05:00 GMT-0800 (PST) | Q96: {=VALUE(INDEX(_xlfn.TEXTSPLIT(P96, " "), 4))} -> 2014 | R96: =_xlfn.TEXTJOIN(" ", TRUE, B96, C96, D96) -> Ford Fusion SE | S96: {=_xlfn.IFS(I96 >= 40, "High", I96>=20, "Medium", I96<20, "Low")} -> Low | T96: {=_xlfn.IFS(O96<18200, "Low", O96<=50000, "Medium", O96>50000, "High")} -> Low
A97: 2014 | B97: BMW | C97: 6 Series | D97: 650i | E97: Convertible | F97: automatic | G97: wbayp9c53ed169288 | H97: ca | I97: 37 | J97: 8891 | K97: silver | L97: black | M97: the hertz corporation | N97: 68000 | O97: 67200 | P97: Wed Dec 17 2014 12:30:00 GMT-0800 (PST) | Q97: {=VALUE(INDEX(_xlfn.TEXTSPLIT(P97, " "), 4))} -> 2014 | R97: =_xlfn.TEXTJOIN(" ", TRUE, B97, C97, D97) -> BMW 6 Series 650i | S97: {=_xlfn.IFS(I97 >= 40, "High", I97>=20, "Medium", I97<20, "Low")} -> Medium | T97: {=_xlfn.IFS(O97<18200, "Low", O97<=50000, "Medium", O97>50000, "High")} -> High
A98: 2014 | B98: Chevrolet | C98: Cruze | D98: 2LT | E98: Sedan | F98: automatic | G98: 1g1pe5sb8e7420706 | H98: ca | I98: 2 | J98: 8154 | K98: silver | L98: black | M98: enterprise vehicle exchange / tra / rental / tulsa | N98: 14150 | O98: 10000 | P98: Thu Dec 18 2014 12:00:00 GMT-0800 (PST) | Q98: {=VALUE(INDEX(_xlfn.TEXTSPLIT(P98, " "), 4))} -> 2014 | R98: =_xlfn.TEXTJOIN(" ", TRUE, B98, C98, D98) -> Chevrolet Cruze 2LT | S98: {=_xlfn.IFS(I98 >= 40, "High", I98>=20, "Medium", I98<20, "Low")} -> Low | T98: {=_xlfn.IFS(O98<18200, "Low", O98<=50000, "Medium", O98>50000, "High")} -> Low
A99: 2014 | B99: Chevrolet | C99: Silverado 1500 | D99: LT | E99: Crew Cab | F99: automatic | G99: 3gcpcrecxeg363552 | H99: ca | I99: 37 | J99: 6726 | K99: black | L99: black | M99: repo remarketing/visterra credit union | N99: 26900 | O99: 30250 | P99: Wed Dec 17 2014 12:30:00 GMT-0800 (PST) | Q99: {=VALUE(INDEX(_xlfn.TEXTSPLIT(P99, " "), 4))} -> 2014 | R99: =_xlfn.TEXTJOIN(" ", TRUE, B99, C99, D99) -> Chevrolet Silverado 1500 LT | S99: {=_xlfn.IFS(I99 >= 40, "High", I99>=20, "Medium", I99<20, "Low")} -> Medium | T99: {=_xlfn.IFS(O99<18200, "Low", O99<=50000, "Medium", O99>50000, "High")} -> Medium
A100: 2014 | B100: Chevrolet | C100: Cruze | D100: 2LT | E100: Sedan | F100: automatic | G100: 1g1pe5sb4e7109323 | H100: ca | I100: 37 | J100: 36771 | K100: silver | L100: black | M100: avis rac/san leandro | N100: 13000 | O100: 13600 | P100: Wed Dec 17 2014 12:30:00 GMT-0800 (PST) | Q100: {=VALUE(INDEX(_xlfn.TEXTSPLIT(P100, " "), 4))} -> 2014 | R100: =_xlfn.TEXTJOIN(" ", TRUE, B100, C100, D100) -> Chevrolet Cruze 2LT | S100: {=_xlfn.IFS(I100 >= 40, "High", I100>=20, "Medium", I100<20, "Low")} -> Medium | T100: {=_xlfn.IFS(O100<18200, "Low", O100<=50000, "Medium", O100>50000, "High")} -> Low
A101: 2015 | B101: Kia | C101: Sorento | D101: LX | E101: SUV | F101: automatic | G101: 5xyktca67fg567068 | H101: ca | I101: 49 | J101: 9552 | K101: burgundy | L101: beige | M101: kia motors america inc | N101: 20800 | O101: 21000 | P101: Tue Dec 16 2014 12:30:00 GMT-0800 (PST) | Q101: {=VALUE(INDEX(_xlfn.TEXTSPLIT(P101, " "), 4))} -> 2014 | R101: =_xlfn.TEXTJOIN(" ", TRUE, B101, C101, D101) -> Kia Sorento LX | S101: {=_xlfn.IFS(I101 >= 40, "High", I101>=20, "Medium", I101<20, "Low")} -> High | T101: {=_xlfn.IFS(O101<18200, "Low", O101<=50000, "Medium", O101>50000, "High")} -> Medium
A102: 2014 | B102: Chevrolet | C102: Cruze | D102: 2LT | E102: Sedan | F102: automatic | G102: 1g1pe5sb3e7406616 | H102: ca | I102: 1 | J102: 10673 | K102: red | L102: black | M102: enterprise vehicle exchange / tra / rental / tulsa | N102: 14150 | O102: 3300 | P102: Tue Dec 16 2014 13:00:00 GMT-0800 (PST) | Q102: {=VALUE(INDEX(_xlfn.TEXTSPLIT(P102, " "), 4))} -> 2014 | R102: =_xlfn.TEXTJOIN(" ", TRUE, B102, C102, D102) -> Chevrolet Cruze 2LT | S102: {=_xlfn.IFS(I102 >= 40, "High", I102>=20, "Medium", I102<20, "Low")} -> Low | T102: {=_xlfn.IFS(O102<18200, "Low", O102<=50000, "Medium", O102>50000, "High")} -> Low
A103: 2015 | B103: Volvo | C103: V60 | D103: T5 | E103: Wagon | F103: automatic | G103: yv1612sb6f1202338 | H103: ca | I103: 37 | J103: 14806 | K103: white | L103: beige | M103: volvo na rep/world omni | N103: 30700 | O103: 30000 | P103: Thu Dec 18 2014 12:30:00 GMT-0800 (PST) | Q103: {=VALUE(INDEX(_xlfn.TEXTSPLIT(P103, " "), 4))} -> 2014 | R103: =_xlfn.TEXTJOIN(" ", TRUE, B103, C103, D103) -> Volvo V60 T5 | S103: {=_xlfn.IFS(I103 >= 40, "High", I103>=20, "Medium", I103<20, "Low")} -> Medium | T103: {=_xlfn.IFS(O103<18200, "Low", O103<=50000, "Medium", O103>50000, "High")} -> Medium
A104: 2014 | B104: Chevrolet | C104: Camaro | D104: LS | E104: Coupe | F104: manual | G104: 2g1fe1e34e9190976 | H104: ca | I104: 44 | J104: 7924 | K104: white | L104: black | M104: tdaf remarketing | N104: 17850 | O104: 18500 | P104: Tue Dec 16 2014 12:30:00 GMT-0800 (PST) | Q104: {=VALUE(INDEX(_xlfn.TEXTSPLIT(P104, " "), 4))} -> 2014 | R104: =_xlfn.TEXTJOIN(" ", TRUE, B104, C104, D104) -> Chevrolet Camaro LS | S104: {=_xlfn.IFS(I104 >= 40, "High", I104>=20, "Medium", I104<20, "Low")} -> High | T104: {=_xlfn.IFS(O104<18200, "Low", O104<=50000, "Medium", O104>50000, "High")} -> Medium
A105: 2015 | B105: Nissan | C105: Altima | D105: 2.5 S | E105: Sedan | F105: automatic | G105: 1n4al3ap4fn310470 | H105: ca | I105: 1 | J105: 12752 | K105: gray | L105: black | M105: enterprise vehicle exchange / tra / rental / tulsa | N105: 14600 | O105: 9500 | P105: Tue Dec 30 2014 13:00:00 GMT-0800 (PST) | Q105: {=VALUE(INDEX(_xlfn.TEXTSPLIT(P105, " "), 4))} -> 2014 | R105: =_xlfn.TEXTJOIN(" ", TRUE, B105, C105, D105) -> Nissan Altima 2.5 S | S105: {=_xlfn.IFS(I105 >= 40, "High", I105>=20, "Medium", I105<20, "Low")} -> Low | T105: {=_xlfn.IFS(O105<18200, "Low", O105<=50000, "Medium", O105>50000, "High")} -> Low
... A113: 2015 | B113: Hyundai | C113: Elantra | D113: SE | E113: Sedan | F113: automatic | G113: 5npdh4ae8fh565992 | H113: ca | I113: 2 | J113: 7800 | K113: silver | L113: gray | M113: enterprise vehicle exchange / tra / rental / tulsa | N113: 13800 | O113: 9000 | P113: Tue Dec 16 2014 12:00:00 GMT-0800 (PST) | Q113: {=VALUE(INDEX(_xlfn.TEXTSPLIT(P113, " "), 4))} -> 2014 | R113: =_xlfn.TEXTJOIN(" ", TRUE, B113, C113, D113) -> Hyundai Elantra SE | S113: {=_xlfn.IFS(I113 >= 40, "High", I113>=20, "Medium", I113<20, "Low")} -> Low | T113: {=_xlfn.IFS(O113<18200, "Low", O113<=50000, "Medium", O113>50000, "High")} -> Low
A114: 2014 | B114: Chevrolet | C114: Cruze | D114: 1LT | E114: Sedan | G114: 1g1pc5sbxe7113253 | H114: ca | I114: 28 | J114: 40393 | K114: gray | L114: black | M114: avis corporation | N114: 11450 | O114: 11700 | P114: Tue Dec 30 2014 15:00:00 GMT-0800 (PST) | Q114: {=VALUE(INDEX(_xlfn.TEXTSPLIT(P114, " "), 4))} -> 2014 | R114: =_xlfn.TEXTJOIN(" ", TRUE, B114, C114, D114) -> Chevrolet Cruze 1LT | S114: {=_xlfn.IFS(I114 >= 40, "High", I114>=20, "Medium", I114<20, "Low")} -> Medium | T114: {=_xlfn.IFS(O114<18200, "Low", O114<=50000, "Medium", O114>50000, "High")} -> Low
A115: 2014 | B115: Chevrolet | C115: Silverado 1500 | D115: LT | E115: Crew Cab | F115: automatic | G115: 3gcukrec9eg452373 | H115: ca | I115: 4 | J115: 9685 | K115: white | L115: black | M115: ars/acme auto leasing | N115: 31700 | O115: 30000 | P115: Thu Dec 18 2014 12:00:00 GMT-0800 (PST) | Q115: {=VALUE(INDEX(_xlfn.TEXTSPLIT(P115, " "), 4))} -> 2014 | R115: =_xlfn.TEXTJOIN(" ", TRUE, B115, C115, D115) -> Chevrolet Silverado 1500 LT | S115: {=_xlfn.IFS(I115 >= 40, "High", I115>=20, "Medium", I115<20, "Low")} -> Low | T115: {=_xlfn.IFS(O115<18200, "Low", O115<=50000, "Medium", O115>50000, "High")} -> Medium
A116: 2015 | B116: Kia | C116: Sorento | D116: LX | E116: SUV | F116: automatic | G116: 5xyktca60fg570829 | H116: ca | I116: 5 | J116: 10615 | K116: burgundy | L116: black | M116: kia motors america inc | N116: 20700 | O116: 20500 | P116: Tue Dec 16 2014 12:30:00 GMT-0800 (PST) | Q116: {=VALUE(INDEX(_xlfn.TEXTSPLIT(P116, " "), 4))} -> 2014 | R116: =_xlfn.TEXTJOIN(" ", TRUE, B116, C116, D116) -> Kia Sorento LX | S116: {=_xlfn.IFS(I116 >= 40, "High", I116>=20, "Medium", I116<20, "Low")} -> Low | T116: {=_xlfn.IFS(O116<18200, "Low", O116<=50000, "Medium", O116>50000, "High")} -> Medium
A117: 2015 | B117: Kia | C117: Sorento | D117: LX | E117: SUV | F117: automatic | G117: 5xyktca61fg560973 | H117: ca | I117: 48 | J117: 13031 | K117: purple | L117: black | M117: kia motors america inc | N117: 20600 | O117: 20750 | P117: Tue Dec 16 2014 12:30:00 GMT-0800 (PST) | Q117: {=VALUE(INDEX(_xlfn.TEXTSPLIT(P117, " "), 4))} -> 2014 | R117: =_xlfn.TEXTJOIN(" ", TRUE, B117, C117, D117) -> Kia Sorento LX | S117: {=_xlfn.IFS(I117 >= 40, "High", I117>=20, "Medium", I117<20, "Low")} -> High | T117: {=_xlfn.IFS(O117<18200, "Low", O117<=50000, "Medium", O117>50000, "High")} -> Medium
...

Sheet Price_vs_odometer
B3: Column Labels
B4: High | C4: Low | D4: Medium | E4: Grand Total
A5: Count of car_full_name | B5: 771 | C5: 342 | D5: 886 | E5: 1999
B10: Column Labels
B11: High | C11: Low | D11: Medium | E11: Grand Total
A12: Count of price_flag | B12: 771 | C12: 342 | D12: 886 | E12: 1999
